xpt2csv/__init__.py
xpt2csv/to_csv.py
xpt2csv-0.1.0.dist-info/METADATA
xpt2csv-0.1.0.dist-info/WHEEL
xpt2csv-0.1.0.dist-info/top_level.txt
xpt2csv-0.1.0.dist-info/RECORD
