Metadata-Version: 2.1
Name: xpt2csv
Version: 0.1.0
Summary: My first Python library
Author: Yousuf Ali
